odoo/addons/mail_activity_reply_creator/README.rst
odoo/addons/mail_activity_reply_creator/__init__.py
odoo/addons/mail_activity_reply_creator/__manifest__.py
odoo/addons/mail_activity_reply_creator/i18n/it.po
odoo/addons/mail_activity_reply_creator/i18n/mail_activity_reply_creator.pot
odoo/addons/mail_activity_reply_creator/models/__init__.py
odoo/addons/mail_activity_reply_creator/models/mail_activity.py
odoo/addons/mail_activity_reply_creator/readme/CONTRIBUTORS.rst
odoo/addons/mail_activity_reply_creator/readme/DESCRIPTION.rst
odoo/addons/mail_activity_reply_creator/static/description/icon.png
odoo/addons/mail_activity_reply_creator/static/description/index.html
odoo/addons/mail_activity_reply_creator/tests/__init__.py
odoo/addons/mail_activity_reply_creator/tests/test_mail_activity_reply_creator.py
odoo_addon_mail_activity_reply_creator-16.0.1.0.0.2.dist-info/METADATA
odoo_addon_mail_activity_reply_creator-16.0.1.0.0.2.dist-info/WHEEL
odoo_addon_mail_activity_reply_creator-16.0.1.0.0.2.dist-info/top_level.txt
odoo_addon_mail_activity_reply_creator-16.0.1.0.0.2.dist-info/RECORD
