Metadata-Version: 2.1
Name: odoo-addon-mail_activity_reply_creator
Version: 16.0.1.0.0.2
Summary: Assign new to its creator
Home-page: https://github.com/OCA/social
Author: Ilyas, Ooops, Odoo Community Association (OCA)
Author-email: support@odoo-community.org
License: AGPL-3
Classifier: Programming Language :: Python
Classifier: Framework :: Odoo
Classifier: Framework :: Odoo :: 16.0
Classifier: License :: OSI Approved :: GNU Affero General Public License v3
Requires-Python: >=3.10
Requires-Dist: odoo<16.1dev,>=16.0a
